office_word_mcp_server/__init__.py
word_document_server/__init__.py
word_document_server/main.py
word_document_server/core/__init__.py
word_document_server/core/footnotes.py
word_document_server/core/protection.py
word_document_server/core/styles.py
word_document_server/core/tables.py
word_document_server/core/unprotect.py
word_document_server/tools/__init__.py
word_document_server/tools/content_tools.py
word_document_server/tools/document_tools.py
word_document_server/tools/extended_document_tools.py
word_document_server/tools/footnote_tools.py
word_document_server/tools/format_tools.py
word_document_server/tools/protection_tools.py
word_document_server/utils/__init__.py
word_document_server/utils/document_utils.py
word_document_server/utils/extended_document_utils.py
word_document_server/utils/file_utils.py
word_mcp_server-0.0.3.dist-info/METADATA
word_mcp_server-0.0.3.dist-info/WHEEL
word_mcp_server-0.0.3.dist-info/entry_points.txt
word_mcp_server-0.0.3.dist-info/licenses/LICENSE
word_mcp_server-0.0.3.dist-info/RECORD
