Metadata-Version: 2.4
Name: word-mcp-server
Version: 0.0.3
Summary: MCP server for manipulating Microsoft Word documents
Project-URL: Homepage, https://github.com/GongRzhe/Office-Word-MCP-Server.git
Project-URL: Bug Tracker, https://github.com/GongRzhe/Office-Word-MCP-Server.git/issues
Author-email: GongRzhe <gongrzhe@gmail.com>
License: MIT License
License-File: LICENSE
Classifier: License :: OSI Approved :: MIT License
Classifier: Operating System :: OS Independent
Classifier: Programming Language :: Python :: 3
Requires-Python: >=3.11
Requires-Dist: docx2pdf>=0.1.8
Requires-Dist: fastmcp>=2.8.1
Requires-Dist: msoffcrypto-tool>=5.4.2
Requires-Dist: python-docx>=1.1.2
